{"version": "1.1.0",
 "packagesDir": ".lake/packages",
 "packages":
 [{"type": "path",
   "scope": "",
   "name": "crucible",
   "manifestFile": "lake-manifest.json",
   "inherited": false,
   "dir": "../crucible",
   "configFile": "lakefile.lean"},
  {"type": "path",
   "scope": "",
   "name": "wisp",
   "manifestFile": "lake-manifest.json",
   "inherited": false,
   "dir": "../wisp",
   "configFile": "lakefile.lean"},
  {"type": "path",
   "scope": "",
   "name": "terminus",
   "manifestFile": "lake-manifest.json",
   "inherited": false,
   "dir": "../terminus",
   "configFile": "lakefile.lean"},
  {"url": "https://github.com/argumentcomputer/LSpec",
   "type": "git",
   "subDir": null,
   "scope": "",
   "rev": "fdf848d6cda9f080a09e49e760e2d6f70878800b",
   "name": "LSpec",
   "manifestFile": "lake-manifest.json",
   "inputRev": "main",
   "inherited": true,
   "configFile": "lakefile.toml"}],
 "name": "enchiridion",
 "lakeDir": ".lake"}
